carbon3d/__init__.py
carbon3d/api_client.py
carbon3d/configuration.py
carbon3d/exceptions.py
carbon3d/rest.py
carbon3d/api/__init__.py
carbon3d/api/applications_api.py
carbon3d/api/attachments_api.py
carbon3d/api/builds_api.py
carbon3d/api/model_program_runs_api.py
carbon3d/api/models_api.py
carbon3d/api/part_measurement_templates_api.py
carbon3d/api/part_measurements_api.py
carbon3d/api/part_orders_api.py
carbon3d/api/parts_api.py
carbon3d/api/print_orders_api.py
carbon3d/api/print_quality_data_api.py
carbon3d/api/printed_parts_api.py
carbon3d/api/printers_api.py
carbon3d/api/prints_api.py
carbon3d/api/queues_api.py
carbon3d/models/__init__.py
carbon3d/models/application.py
carbon3d/models/applications_response.py
carbon3d/models/build.py
carbon3d/models/build_attachments.py
carbon3d/models/build_part_orders.py
carbon3d/models/builds_response.py
carbon3d/models/double_parameter.py
carbon3d/models/integer_parameter.py
carbon3d/models/model.py
carbon3d/models/model_presigned_upload_url_request.py
carbon3d/models/model_presigned_upload_url_response.py
carbon3d/models/model_print.py
carbon3d/models/model_program_operation.py
carbon3d/models/model_program_operation_all_of.py
carbon3d/models/model_program_run.py
carbon3d/models/model_program_run_all_of.py
carbon3d/models/model_program_run_request.py
carbon3d/models/model_program_run_status_info.py
carbon3d/models/model_program_runs.py
carbon3d/models/model_resolve_upload_request.py
carbon3d/models/models_response.py
carbon3d/models/part.py
carbon3d/models/part_measurement.py
carbon3d/models/part_measurement_response.py
carbon3d/models/part_measurement_template.py
carbon3d/models/part_measurement_template_category_options.py
carbon3d/models/part_measurement_template_response.py
carbon3d/models/part_order.py
carbon3d/models/part_order_request.py
carbon3d/models/part_order_request_parts.py
carbon3d/models/part_order_status.py
carbon3d/models/part_order_update_request.py
carbon3d/models/part_orders_response.py
carbon3d_client-0.4.17.dist-info/METADATA
carbon3d_client-0.4.17.dist-info/WHEEL
carbon3d_client-0.4.17.dist-info/top_level.txt
carbon3d_client-0.4.17.dist-info/RECORD
