Metadata-Version: 2.1
Name: carbon3d-client
Version: 0.4.17
Summary: Carbon DLS API
Home-page: UNKNOWN
Author: Carbon API Support
Author-email: api-list@carbon3d.com
License: UNKNOWN
Keywords: OpenAPI,OpenAPI-Generator,Carbon DLS API
Platform: UNKNOWN
Requires-Dist: urllib3 >=1.15
Requires-Dist: six >=1.10
Requires-Dist: certifi
Requires-Dist: python-dateutil
